Workbook

Sheet 汇总
A1: 货币资金审计底稿 - 核心优化版
A3: 客户名称 | B3: =IF(货币资金主表!B3="","",货币资金主表!B3)
A4: 期末日 | B4: =IF(货币资金主表!B4="","",货币资金主表!B4)
A5: 可容忍误差 | B5: =IF(货币资金主表!B6="","",货币资金主表!B6)
A6: 名义金额 | B6: =IF(货币资金主表!B7="","",货币资金主表!B7)
A7: 记账本位币 | B7: =IF(货币资金主表!B10="","",货币资金主表!B10)
A9: 程序索引
A10: 编号 | B10: 名称 | C10: 主要认定 | D10: 工作目标 | E10: 执行状态 | F10: 编制人 | G10: 复核人 | H10: 链接/索引 | I10: 备注 | J10: 核对
A11: 1 | B11: 货币资金主表 | C11: E / V / C | D11: 汇总风险评估、阈值、余额波动和披露核对。 | E11: 执行 | H11: 货币资金主表 | J11: =IF(货币资金主表!B36="通过","通过","待核对")
A12: 2 | B12: 货币资金明细 | C12: E / V / C | D12: 列示全量货币资金账户，并与主表期末余额核对。 | E12: 执行 | H12: 货币资金明细 | J12: =IF(货币资金明细!B114="通过","通过","待核对")
A13: 3 | B13: 银行余额调节 | C13: E / C | D13: 测试银行余额调节表及未达账项处理。 | E13: 执行 | H13: 银行余额调节 | J13: =IF(银行余额调节!E33="通过","通过","待核对")
A14: 4 | B14: 截止性测试 | C14: E / C | D14: 测试期末前后银行间转账是否记录于恰当期间。 | E14: 执行 | H14: 截止性测试 | J14: =IF(COUNTIF(截止性测试!P13:P57,"<>0")=0,"通过","关注")
A17: 编制与复核
A18: 编制人 | C18: 编制日期 | E18: 复核人 | G18: 复核日期 | I18: 总体备注
A20: 说明 | B20: 黄色区域为输入区；浅蓝区域为公式区；绿色状态为核对通过。

Sheet 货币资金主表
A1: 货币资金主表
A3: 客户名称 | D3: 工作目标 | E3: 记录货币资金余额、账户完整性、重大波动和后续程序结论
A4: 期末日 | D4: 填写说明 | E4: 黄色区域为输入区；浅蓝区域为公式或自动检查区
A5: 分析日期
A6: 可容忍误差
A7: 名义金额
A8: 适用会计准则 | B8: 中国企业会计准则
A9: 审计准则 | B9: 中国注册会计师审计准则
A10: 记账本位币 | B10: CNY
A13: 认定风险与测试阈值
A14: 认定 | B14: CRA 风险等级 | C14: 阈值比例 | D14: 测试阈值 | E14: 说明
A15: 完整性 | C15: =IF(B15="不适用","",IF(B15="极低",1,IF(B15="低",0.75,IF(B15="中等",0.5,IF(B15="高",0.25,""))))) | D15: =IF(C15="","",$B$6*C15) | E15: C.02 / 截止测试取完整性与存在性阈值较小值
A16: 存在性 | C16: =IF(B16="不适用","",IF(B16="极低",1,IF(B16="低",0.75,IF(B16="中等",0.5,IF(B16="高",0.25,""))))) | D16: =IF(C16="","",$B$6*C16)
A17: 准确性/计价 | C17: =IF(B17="不适用","",IF(B17="极低",1,IF(B17="低",0.75,IF(B17="中等",0.5,IF(B17="高",0.25,""))))) | D17: =IF(C17="","",$B$6*C17)
A18: 权利和义务 | C18: =IF(B18="不适用","",IF(B18="极低",1,IF(B18="低",0.75,IF(B18="中等",0.5,IF(B18="高",0.25,""))))) | D18: =IF(C18="","",$B$6*C18)
A19: 列报 | C19: =IF(B19="不适用","",IF(B19="极低",1,IF(B19="低",0.75,IF(B19="中等",0.5,IF(B19="高",0.25,""))))) | D19: =IF(C19="","",$B$6*C19)
A23: 波动比例阈值 | C23: 余额波动同时参考名义金额与比例阈值
A27: 余额波动分析
A28: 账套 | B28: 科目编码 | C28: 科目 | D28: 索引 | E28: 期末账面数 | F28: 账表调整 | G28: 期末未审数 | H28: 审计调整 | I28: 期末审定数 | J28: 上年审定数 | K28: 变动金额 | L28: 变动% | M28: 超阈值 | N28: 说明
C29: 库存现金 | D29: 货币资金明细 | G29: =IF(OR(E29<>"",F29<>""),SUM(E29:F29),"") | I29: =IF(OR(G29<>"",H29<>""),SUM(G29:H29),"") | K29: =IF(OR(I29<>"",J29<>""),I29-J29,"") | L29: =IF(J29<>0,K29/J29,IF(I29<>0,1,0)) | M29: =IF(OR(K29="",$B$7="",$B$23=""),"",IF(OR(ABS(K29)>=$B$7,ABS(L29)>=$B$23),"是","否"))
C30: 银行存款 | D30: 货币资金明细 | G30: =IF(OR(E30<>"",F30<>""),SUM(E30:F30),"") | I30: =IF(OR(G30<>"",H30<>""),SUM(G30:H30),"") | K30: =IF(OR(I30<>"",J30<>""),I30-J30,"") | L30: =IF(J30<>0,K30/J30,IF(I30<>0,1,0)) | M30: =IF(OR(K30="",$B$7="",$B$23=""),"",IF(OR(ABS(K30)>=$B$7,ABS(L30)>=$B$23),"是","否"))
C31: 其他货币资金 | D31: 货币资金明细 | G31: =IF(OR(E31<>"",F31<>""),SUM(E31:F31),"") | I31: =IF(OR(G31<>"",H31<>""),SUM(G31:H31),"") | K31: =IF(OR(I31<>"",J31<>""),I31-J31,"") | L31: =IF(J31<>0,K31/J31,IF(I31<>0,1,0)) | M31: =IF(OR(K31="",$B$7="",$B$23=""),"",IF(OR(ABS(K31)>=$B$7,ABS(L31)>=$B$23),"是","否"))
A33: 合计 | E33: =SUM(E29:E31) | F33: =SUM(F29:F31) | G33: =SUM(G29:G31) | H33: =SUM(H29:H31) | I33: =SUM(I29:I31) | J33: =SUM(J29:J31) | K33: =I33-J33 | L33: =IF(J33<>0,K33/J33,IF(I33<>0,1,0)) | M33: =IF(OR(K33="",$B$7="",$B$23=""),"",IF(OR(ABS(K33)>=$B$7,ABS(L33)>=$B$23),"是","否"))
A35: 与货币资金明细期末本币金额差异 | B35: =货币资金明细!H112-I33
A36: 核对状态 | B36: =IF(ROUND(B35,2)=0,"通过","待核对")
A42: 受限货币资金披露
A44: 项目 | B44: 期末审定数 | C44: 上年审定数 | D44: 差异 | E44: 核对状态 | F44: 说明
A45: 所有权或使用权受限货币资金 | D45: =IF(OR(B45<>"",C45<>""),B45-C45,"") | E45: =IF(ROUND(B45,2)=0,"无受限资金","关注披露")

Sheet 货币资金明细
A1: 货币资金明细
A3: 列示所有货币资金账户，核对至科目余额表
A4: 资料来源：科目余额表 / 函证或银行回函 / 银行流水
A10: 序号 | B10: 公司 | C10: 科目 | D10: 银行 | E10: 账号 | F10: 币种 | G10: 期末金额(原币) | H10: 期末金额(本币) | I10: 用途 | J10: 是否函证 | K10: 替代程序 | L10: 备注
A12: =IF(COUNTA(B12:L12)=0,"",ROW()-11)
A13: =IF(COUNTA(B13:L13)=0,"",ROW()-11)
A14: =IF(COUNTA(B14:L14)=0,"",ROW()-11)
A15: =IF(COUNTA(B15:L15)=0,"",ROW()-11)
A16: =IF(COUNTA(B16:L16)=0,"",ROW()-11)
A17: =IF(COUNTA(B17:L17)=0,"",ROW()-11)
A18: =IF(COUNTA(B18:L18)=0,"",ROW()-11)
A19: =IF(COUNTA(B19:L19)=0,"",ROW()-11)
A20: =IF(COUNTA(B20:L20)=0,"",ROW()-11)
A21: =IF(COUNTA(B21:L21)=0,"",ROW()-11)
A22: =IF(COUNTA(B22:L22)=0,"",ROW()-11)
A23: =IF(COUNTA(B23:L23)=0,"",ROW()-11)
... A111: =IF(COUNTA(B111:L111)=0,"",ROW()-11)
A112: 合计 | G112: =SUM(G12:G111) | H112: =SUM(H12:H111)
A113: 与主表期末审定数差异 | H113: =H112-货币资金主表!I33
A114: 核对状态 | H114: =IF(ROUND(H113,2)=0,"通过","待核对")

Sheet 银行余额调节
A1: 银行余额调节
A3: 测试阈值 | B3: =IF(COUNT(货币资金主表!D15:D16)=0,"",MIN(货币资金主表!D15:D16)) | C3: 用于识别和测试调节项
A4: 截止期间 | C4: 由项目组根据风险评估、账户性质和交易处理周期确定
A5: 选取说明
A6: 结论
A9: 账户信息
A10: 科目 | C10: 索引 | E10: 编制日期
A11: 银行 | C11: 账号 | E11: 币种
A12: 账户性质 | C12: 有无调节项 | E12: 资料
A17: 余额调节表
A18: 账面侧 | B18: 账面金额(原币) | C18: 索引 | D18: 银行侧 | E18: 对账单金额 | F18: 索引 | G18: 备注
A19: 期末账面余额 | D19: 银行对账单余额
A20: 加：银收企未收 | B20: =SUM(B21:B25) | D20: 加：企收银未收 | E20: =SUM(E21:E25)
A21: 明细1 | D21: 明细1
A22: 明细2 | D22: 明细2
A23: 明细3 | D23: 明细3
A24: 明细4 | D24: 明细4
A25: 明细5 | D25: 明细5
A26: 减：银付企未付 | B26: =SUM(B27:B31) | D26: 减：企付银未付 | E26: =SUM(E27:E31)
A27: 明细1 | D27: 明细1
A28: 明细2 | D28: 明细2
A29: 明细3 | D29: 明细3
A30: 明细4 | D30: 明细4
A31: 明细5 | D31: 明细5
A32: 调节后金额 | B32: =B19+B20-B26 | D32: 调节后金额 | E32: =E19+E20-E26
A33: 核对 | B33: =E32-B32 | D33: 核对状态 | E33: =IF(ROUND(B33,2)=0,"通过","待核对")

Sheet 截止性测试
A1: 截止性测试
A3: 测试阈值 | B3: =IF(COUNT(货币资金主表!D15:D16)=0,"",MIN(货币资金主表!D15:D16)) | C3: 用于识别和测试银行间转账
A4: 截止期间 | C4: 例如期末日前后 1 个工作日；可按风险评估延长
A5: 使用的截止期间（工作日）
A6: 选取理由
A7: 结论
A11: 期末前银行间转账
A12: 样本编号 | B12: 付款/收款主体 | C12: 转出银行 | D12: 转出账号 | E12: 付款/收款时间 | F12: 交易编号 | G12: 币种 | H12: 转出金额 | I12: 转入银行 | J12: 转入账号 | K12: 入账日期 | L12: 转入金额 | M12: 跨期是否体现在余额调节表 | N12: 会计处理是否恰当 | O12: 备注 | P12: 核对
P13: =IF(OR(H13<>"",L13<>""),H13+L13,"")
P14: =IF(OR(H14<>"",L14<>""),H14+L14,"")
P15: =IF(OR(H15<>"",L15<>""),H15+L15,"")
P16: =IF(OR(H16<>"",L16<>""),H16+L16,"")
P17: =IF(OR(H17<>"",L17<>""),H17+L17,"")
P18: =IF(OR(H18<>"",L18<>""),H18+L18,"")
P19: =IF(OR(H19<>"",L19<>""),H19+L19,"")
P20: =IF(OR(H20<>"",L20<>""),H20+L20,"")
P21: =IF(OR(H21<>"",L21<>""),H21+L21,"")
P22: =IF(OR(H22<>"",L22<>""),H22+L22,"")
P23: =IF(OR(H23<>"",L23<>""),H23+L23,"")
P24: =IF(OR(H24<>"",L24<>""),H24+L24,"")
... P32: =IF(OR(H32<>"",L32<>""),H32+L32,"")
A36: 期末后银行间转账
A37: 样本编号 | B37: 付款/收款主体 | C37: 转出银行 | D37: 转出账号 | E37: 付款/收款时间 | F37: 交易编号 | G37: 币种 | H37: 转出金额 | I37: 转入银行 | J37: 转入账号 | K37: 入账日期 | L37: 转入金额 | M37: 跨期是否体现在余额调节表 | N37: 会计处理是否恰当 | O37: 备注 | P37: 核对
P38: =IF(OR(H38<>"",L38<>""),H38+L38,"")
P39: =IF(OR(H39<>"",L39<>""),H39+L39,"")
P40: =IF(OR(H40<>"",L40<>""),H40+L40,"")
P41: =IF(OR(H41<>"",L41<>""),H41+L41,"")
P42: =IF(OR(H42<>"",L42<>""),H42+L42,"")
P43: =IF(OR(H43<>"",L43<>""),H43+L43,"")
P44: =IF(OR(H44<>"",L44<>""),H44+L44,"")
P45: =IF(OR(H45<>"",L45<>""),H45+L45,"")
P46: =IF(OR(H46<>"",L46<>""),H46+L46,"")
P47: =IF(OR(H47<>"",L47<>""),H47+L47,"")
P48: =IF(OR(H48<>"",L48<>""),H48+L48,"")
P49: =IF(OR(H49<>"",L49<>""),H49+L49,"")
... P57: =IF(OR(H57<>"",L57<>""),H57+L57,"")
A60: 核对汇总 | O60: 异常样本数 | P60: =COUNTIF(P13:P57,"<>0")
A61: 核对状态 | P61: =IF(P60=0,"通过","关注")
